gitarootools/__init__.py
gitarootools/archive/__init__.py
gitarootools/archive/pakcontainer.py
gitarootools/archive/paktoml.py
gitarootools/archive/xgmcontainer.py
gitarootools/archive/xgmitem.py
gitarootools/archive/xgmtoml.py
gitarootools/audio/__init__.py
gitarootools/audio/imccontainer.py
gitarootools/audio/imctoml.py
gitarootools/audio/subsong.py
gitarootools/cmdline/__init__.py
gitarootools/cmdline/gmo2animnames.py
gitarootools/cmdline/imcpack.py
gitarootools/cmdline/imcunpack.py
gitarootools/cmdline/imx2png.py
gitarootools/cmdline/pakpack.py
gitarootools/cmdline/pakunpack.py
gitarootools/cmdline/png2imx.py
gitarootools/cmdline/subsong2common.py
gitarootools/cmdline/subsong2subimc.py
gitarootools/cmdline/subsong2wav.py
gitarootools/cmdline/subsongconv.py
gitarootools/cmdline/xgmpack.py
gitarootools/cmdline/xgmunpack.py
gitarootools/image/__init__.py
gitarootools/image/imximage.py
gitarootools/miscutils/__init__.py
gitarootools/miscutils/cmdutils.py
gitarootools/miscutils/datautils.py
gitarootools/miscutils/extutils.py
gitarootools/other/__init__.py
gitarootools/other/gmomodel.py
gitarootools-0.1.8.dist-info/LICENSE
gitarootools-0.1.8.dist-info/METADATA
gitarootools-0.1.8.dist-info/WHEEL
gitarootools-0.1.8.dist-info/entry_points.txt
gitarootools-0.1.8.dist-info/RECORD
