Metadata-Version: 2.1
Name: gitarootools
Version: 0.1.8
Summary: command line tools to work with Gitaroo Man game data
Home-page: https://github.com/boringhexi/gitarootools
License: MIT
Author: boringhexi
Author-email: boringhexi@pm.me
Requires-Python: >=3.7,<4.0
Classifier: License :: OSI Approved :: MIT License
Classifier: Programming Language :: Python :: 3
Classifier: Programming Language :: Python :: 3.7
Classifier: Programming Language :: Python :: 3.8
Classifier: Programming Language :: Python :: 3.9
Classifier: Programming Language :: Python :: 3.10
Classifier: Programming Language :: Python :: 3.11
Requires-Dist: pillow (>=9.5.0,<10.0.0)
Requires-Dist: tomlkit (>=0.11.7,<0.12.0)
Project-URL: Repository, https://github.com/boringhexi/gitarootools
